KairoCore/__init__.py
KairoCore/__main__.py
KairoCore/app.py
KairoCore/cli.py
KairoCore/code_generate/__init__.py
KairoCore/code_generate/code_generator.py
KairoCore/code_generate/generate_page.html
KairoCore/code_generate/generator_router.py
KairoCore/common/consts.py
KairoCore/common/errors.py
KairoCore/common/http.py
KairoCore/db_tools/kc_mysql.py
KairoCore/db_tools/kc_redis.py
KairoCore/db_tools/kc_sqlite.py
KairoCore/db_tools/kc_zookeeper.py
KairoCore/docs/CodeGenerateDoc.md
KairoCore/docs/FileUploadDoc.md
KairoCore/docs/HttpSessionDoc.md
KairoCore/docs/KairoInitDoc.md
KairoCore/docs/RabbitMQClientDoc.md
KairoCore/docs/TaskiqDoc.md
KairoCore/docs/TokenUseDoc.md
KairoCore/docs/UseDoc.md
KairoCore/example/your_project_name/main.py
KairoCore/example/your_project_name/action/api_key_admin.py
KairoCore/example/your_project_name/action/auth.py
KairoCore/example/your_project_name/action/file_upload.py
KairoCore/example/your_project_name/action/http_demo.py
KairoCore/example/your_project_name/action/protected_demo.py
KairoCore/example/your_project_name/action/taskiq_demo.py
KairoCore/example/your_project_name/action/user.py
KairoCore/example/your_project_name/common/consts.py
KairoCore/example/your_project_name/common/errors.py
KairoCore/example/your_project_name/dao/__init__.py
KairoCore/example/your_project_name/dao/user.py
KairoCore/example/your_project_name/dao/user_sqlite.py
KairoCore/example/your_project_name/domain/__init__.py
KairoCore/example/your_project_name/domain/user.py
KairoCore/example/your_project_name/schema/auth.py
KairoCore/example/your_project_name/schema/user.py
KairoCore/extensions/baidu/yijian.py
KairoCore/imgs/__init__.py
KairoCore/imgs/code_generator.png
KairoCore/imgs/favicon.ico
KairoCore/imgs/logo-pixel-128.jpg
KairoCore/imgs/logo-pixel-16.jpg
KairoCore/imgs/logo-pixel-256.jpg
KairoCore/imgs/logo-pixel-32.jpg
KairoCore/imgs/logo-pixel-512.jpg
KairoCore/imgs/logo-pixel-64.jpg
KairoCore/imgs/logo-pixel.png
KairoCore/imgs/logo.png
kairocore-1.5.0.dist-info/METADATA
kairocore-1.5.0.dist-info/WHEEL
kairocore-1.5.0.dist-info/entry_points.txt
kairocore-1.5.0.dist-info/top_level.txt
kairocore-1.5.0.dist-info/RECORD
