Metadata-Version: 2.4
Name: KairoCore
Version: 1.5.0
Summary: 时机，即是智能 —— 为关键时刻而生的核心API引擎。
Author-email: Fatosy <fatosy_code@163.com>
License: MIT
Project-URL: Homepage, https://github.com/Fatosy/KairoCore
Project-URL: Repository, https://github.com/Fatosy/KairoCore.git
Keywords: KairoCore,fastapi,framework,web,api
Classifier: Development Status :: 4 - Beta
Classifier: Intended Audience :: Developers
Classifier: Topic :: Software Development :: Libraries :: Application Frameworks
Classifier: License :: OSI Approved :: MIT License
Classifier: Programming Language :: Python :: 3
Classifier: Programming Language :: Python :: 3.12
Requires-Python: >=3.12
Requires-Dist: fastapi>=0.116.1
Requires-Dist: uvicorn>=0.35.0
Requires-Dist: python-dotenv>=1.1.1
Requires-Dist: redis>=6.4.0
Requires-Dist: kazoo>=2.10.0
Requires-Dist: pymysql>=1.1.2
Requires-Dist: DBUtils>=3.1.2
Requires-Dist: aiomysql>=0.2.0
Requires-Dist: cryptography>=45.0.7
Requires-Dist: pytz>=2025.2
Requires-Dist: aiozk>=0.32.0
Requires-Dist: jinja2>=3.1.6
Requires-Dist: httpx>=0.28.1
Requires-Dist: starlette>=0.47.3
Requires-Dist: python-multipart>=0.0.9
Requires-Dist: cryptography>=45.0.7
Requires-Dist: pika>=1.3.2
Requires-Dist: taskiq>=0.11.9
Requires-Dist: taskiq-redis>=1.0.1
